{
  "sources": [
    {
      "name": "YanG-1989 Gather",
      "url": "https://tv.iill.top/m3u/Gather",
      "priority": 30,
      "region": "cn",
      "epg": true,
      "logo": true
    },
    {
      "name": "ZBDS IPv4",
      "url": "https://live.zbds.org/tv/iptv4.m3u",
      "priority": 28,
      "region": "cn",
      "epg": true,
      "logo": true
    },
    {
      "name": "ZBDS IPv4 Mirror",
      "url": "https://live.zbds.top/tv/iptv4.m3u",
      "priority": 27,
      "region": "cn",
      "epg": true,
      "logo": true
    },
    {
      "name": "EPG.pw China HTTPS",
      "url": "https://epg.pw/test_channels_china.m3u",
      "priority": 6,
      "region": "global",
      "epg": true,
      "logo": true,
      "preferTitleName": true
    },
    {
      "name": "Guovin IPv4",
      "url": "https://raw.githubusercontent.com/Guovin/iptv-api/gd/output/ipv4/result.m3u",
      "priority": 26,
      "region": "cn",
      "epg": true,
      "logo": true
    },
    {
      "name": "myIPTV IPv4",
      "url": "https://raw.githubusercontent.com/suxuang/myIPTV/refs/heads/main/ipv4.m3u",
      "priority": 24,
      "region": "cn",
      "epg": true,
      "logo": true
    },
    {
      "name": "zwc456baby Alive",
      "url": "https://raw.githubusercontent.com/zwc456baby/iptv_alive/refs/heads/master/live.m3u",
      "priority": 22,
      "region": "cn",
      "epg": true,
      "logo": true
    },
    {
      "name": "Kimentanm APTV",
      "url": "https://raw.githubusercontent.com/Kimentanm/aptv/master/m3u/iptv.m3u",
      "priority": 18,
      "region": "cn",
      "epg": true,
      "logo": false
    },
    {
      "name": "Fanmingming IPv6",
      "url": "https://live.fanmingming.cn/tv/m3u/ipv6.m3u",
      "priority": 17,
      "region": "cn",
      "epg": true,
      "logo": true
    },
    {
      "name": "Ibert Fanmingming IPv6",
      "url": "https://m3u.ibert.me/fmml_ipv6.m3u",
      "priority": 15,
      "region": "cn",
      "epg": true,
      "logo": true
    },
    {
      "name": "YueChan Live",
      "url": "https://raw.githubusercontent.com/YueChan/Live/refs/heads/main/IPTV.m3u",
      "priority": 16,
      "region": "cn",
      "epg": false,
      "logo": true
    },
    {
      "name": "ChinaIPTV AutoUpdate",
      "url": "https://raw.githubusercontent.com/hujingguang/ChinaIPTV/main/cnTV_AutoUpdate.m3u8",
      "priority": 14,
      "region": "cn",
      "epg": false,
      "logo": true
    },
    {
      "name": "Collect IPTV Auto",
      "url": "https://raw.githubusercontent.com/zilong7728/Collect-IPTV/refs/heads/main/best_sorted.m3u",
      "priority": 13,
      "region": "cn",
      "epg": false,
      "logo": true
    },
    {
      "name": "BurningC4 Chinese IPTV",
      "url": "https://raw.githubusercontent.com/BurningC4/Chinese-IPTV/master/TV-IPV4.m3u",
      "priority": 10,
      "region": "cn",
      "epg": false,
      "logo": false
    },
    {
      "name": "IPTV org Chinese Fallback",
      "url": "https://iptv-org.github.io/iptv/languages/zho.m3u",
      "priority": 8,
      "region": "global",
      "epg": false,
      "logo": true
    }
  ],
  "preferredKeywords": [
    "CCTV",
    "央视",
    "中央",
    "CGTN",
    "凤凰",
    "Phoenix",
    "TVB",
    "香港",
    "翡翠",
    "明珠",
    "港台",
    "卫视",
    "湖南",
    "浙江",
    "东方",
    "江苏",
    "广东",
    "北京",
    "深圳",
    "台湾",
    "TVBS",
    "民视",
    "三立",
    "中天",
    "东森",
    "华视",
    "中视",
    "台视",
    "风云",
    "剧场",
    "怀旧",
    "世界地理",
    "兵器",
    "女性时尚",
    "台球",
    "高尔夫",
    "卡通",
    "少儿",
    "动漫",
    "动画",
    "金鹰",
    "卡酷",
    "优漫",
    "嘉佳",
    "哈哈",
    "炫动",
    "游戏风云",
    "梨园",
    "法治天地",
    "劲爆体育"
  ],
  "requiredKeywords": [
    "CCTV",
    "CGTN",
    "央视",
    "中央",
    "中国",
    "中文",
    "Chinese",
    "Mandarin",
    "Cantonese",
    "凤凰",
    "Phoenix",
    "TVB",
    "香港",
    "港台",
    "台湾",
    "卫视",
    "湖南",
    "浙江",
    "东方",
    "江苏",
    "广东",
    "北京",
    "深圳",
    "TVBS",
    "民视",
    "三立",
    "中天",
    "东森",
    "华视",
    "中视",
    "台视",
    "风云",
    "剧场",
    "怀旧",
    "世界地理",
    "兵器",
    "女性时尚",
    "台球",
    "高尔夫",
    "卡通",
    "少儿",
    "动漫",
    "动画",
    "金鹰",
    "卡酷",
    "优漫",
    "嘉佳",
    "哈哈",
    "炫动",
    "游戏风云",
    "梨园",
    "法治天地",
    "劲爆体育"
  ],
  "blockedKeywords": [
    "广告",
    "推广",
    "引流",
    "关注",
    "支持",
    "作者",
    "app",
    "apk",
    "下载",
    "群",
    "测试",
    "购物",
    "radio",
    "广播",
    "backup",
    "demo",
    "斗鱼",
    "虎牙",
    "熊猫",
    "bilibili",
    "博彩",
    "成人",
    "xxx",
    "bet",
    "casino",
    "hbo",
    "showtime",
    "starz",
    "cinemax",
    "espn",
    "nba",
    "nfl",
    "mlb",
    "ufc",
    "disney",
    "cartoon network",
    "nickelodeon",
    "national geographic",
    "nat geo"
  ],
  "blockedUrlKeywords": [
    "youtube.com/",
    "youtu.be/",
    "advertisingId=",
    "ads.",
    "appName=",
    "appVersion=",
    "rokuChannel",
    "nosignal"
  ],
  "maxChannels": 160,
  "maxSourcesPerChannel": 8,
  "maxSourcePoolPerChannel": 40,
  "generatedSourceFamilies": [
    {
      "name": "IPTV org CCTV 69 Family",
      "urlTemplate": "http://69.30.245.50/live/cctv{number}.m3u8",
      "channels": [
        "CCTV-1",
        "CCTV-2",
        "CCTV-3",
        "CCTV-4",
        "CCTV-5",
        "CCTV-6",
        "CCTV-7",
        "CCTV-8",
        "CCTV-9",
        "CCTV-10"
      ],
      "priority": 34,
      "region": "global",
      "group": "央视频道"
    },
    {
      "name": "IPTV org CCTV 74 HD Family",
      "urlTemplate": "http://74.91.26.218:82/live/cctv{number}hd.m3u8",
      "channels": [
        "CCTV-1",
        "CCTV-2",
        "CCTV-3",
        "CCTV-4",
        "CCTV-5",
        "CCTV-6",
        "CCTV-7",
        "CCTV-8",
        "CCTV-9",
        "CCTV-10",
        "CCTV-11",
        "CCTV-12",
        "CCTV-13",
        "CCTV-14",
        "CCTV-15",
        "CCTV-16",
        "CCTV-17"
      ],
      "priority": 35,
      "region": "global",
      "group": "央视频道"
    }
  ],
  "manualSources": [
    {
      "name": "CCTV-5",
      "group": "央视频道",
      "url": "https://api.olelive.com/dis/live/CCTV5HD/hls.m3u8",
      "origin": "OleLive Manual",
      "priority": 6,
      "region": "global"
    }
  ],
  "sourcePreferences": {
    "CCTV-13": [
      "http://ali-m-l.cztv.com/channels/lantian/channel21/1080p.m3u8"
    ],
    "CCTV-5": [
      "http://69.30.245.50/live/cctv5.m3u8",
      "http://74.91.26.218:82/live/cctv5hd.m3u8",
      "http://112.27.235.94:8000/hls/5/index.m3u8"
    ]
  },
  "healthCheck": {
    "enabled": true,
    "timeoutMs": 6500,
    "concurrency": 20,
    "maxSourcesToCheck": 3200,
    "maxCandidatesPerChannel": 90,
    "minimumPlayableChannels": 30
  }
}
